{
  "Result": true,
  "ErrorMessage": null,
  "ErrorCode": 0,
  "Response": {
    "transArray": [
      {
        "transKey": "NWd+4ZBb1RcU1hu9GMoSNQSukcz/gXF3Pp/RJ9XN7lkHR6WKZjgqKg==_review_488502586",
        "content": "Very modern, come on"
      },
      {
        "transKey": "C2/vQw5sZMxBKvuVEE7QxxrAjLhBcu2/j0Jifk0K7EgHR6WKZjgqKg==_review_488611567",
        "content": "In the bustling and busy urban life, you are running around in dreams and similarities. I hope our small efforts can bring you joy. Your satisfaction is our greatest support and encouragement. I believe we will all do better. Thank you. For your support, I wish you a happy life!"
      }
    ]
  },
  "ServerData": null
}