{
  "Result": true,
  "ErrorMessage": null,
  "ErrorCode": 0,
  "Response": {
    "transArray": [
      {
        "transKey": "jz5DQ400oo2oCTG40jPWkTUbgc/9OoQ3oPRrTpR0tUEHR6WKZjgqKg==_review_887980185",
        "content": "The room is clean but too small"
      },
      {
        "transKey": "akiRknLo8m4EBs76SzEU5VG6ih2T4G/1kDLlsuCPKJ4HR6WKZjgqKg==_review_888699387",
        "content": "Thank you for staying in our hotel. The area of ​​our double bed room A that you stayed in may be a bit small. Next time, you can try our zero-pressure superior double room, which is spacious. The bedding is imported memory foam pillows and mattresses. It's very comfortable and stress-relieving to go up there. All hotel staff look forward to your visit again"
      }
    ]
  },
  "ServerData": null
}