{
  "Result": true,
  "ErrorMessage": null,
  "ErrorCode": 0,
  "Response": {
    "transArray": [
      {
        "transKey": "n3dS5tYBLTee2WzH4ngBR/Y8BoPAQ7HsWFxFMdKDe7sHR6WKZjgqKg==_review_630092161",
        "content": "The service is very good, clean and comfortable"
      },
      {
        "transKey": "yrl1m8C3+iDlblKjfXRvt8IK9x6glF0QJur5oeM6OVwHR6WKZjgqKg==_review_630669373",
        "content": "The water is growing in autumn, the spring forest is blooming in autumn, and the spring breeze is ten miles away. I hope you will accompany me in Xiaoji. Thank you for your support."
      }
    ]
  },
  "ServerData": null
}