{
  "Result": true,
  "ErrorMessage": null,
  "ErrorCode": 0,
  "Response": {
    "transArray": [
      {
        "transKey": "/kzT6l8/TW/oJUjjaxyz+FdpELT4ihtPPqRNFy75Kw4HR6WKZjgqKg==_review_612003195",
        "content": "The front desk service is very good. The lobby environment is very comfortable. The rooms are nice. The robot in the lobby delivers takeaways to the room."
      },
      {
        "transKey": "MfiS9/vaEMp8udJtHlRzdgJorf9Iui/MPmLds2ds1IIHR6WKZjgqKg==_review_612014409",
        "content": "May time slow down, may old friends never be separated, with your company, Xiao Ji will never be alone! Thank you for staying here, friends. We will be with you wholeheartedly throughout the seasons! Looking forward to every stay with you~"
      }
    ]
  },
  "ServerData": null
}