{
  "Result": true,
  "ErrorMessage": null,
  "ErrorCode": 0,
  "Response": {
    "transArray": [
      {
        "transKey": "1sw09PX8GLSVrcJXqDeN7OVMER/u8VABsQtzc6JADJgHR6WKZjgqKg==_review_757406113",
        "content": "It's the third day the hotel has been newly opened. There is no decoration smell, which is great. The environment and services are very good, sugar is prepared in the room, and the breakfast is also rich."
      },
      {
        "transKey": "9FzL//fLhrXSIOrSSkbGRW1LHXY3xnrBMtgnms++3nIHR6WKZjgqKg==_review_757924079",
        "content": "Dear guests: Hello! Thank you very much for your stay and appreciation! Glad to have a great time with you on your outing. Your appreciation is a great encouragement to the hotel and the driving force for our progress. We will continue to maintain our enthusiasm and strive to make every guest feel at home. We look forward to your visit again! Welcome to come back to experience again, I wish you a happy life!"
      }
    ]
  },
  "ServerData": null
}