{
  "Result": true,
  "ErrorMessage": null,
  "ErrorCode": 0,
  "Response": {
    "transArray": [
      {
        "transKey": "ZXKzX2KVCg4ESnoG5L1LnnO7ExW+hJwf8BfXMrNjnvMHR6WKZjgqKg==_review_805771917",
        "content": "Satisfied, you can eat as many oranges as you want, and the service attitude is great"
      },
      {
        "transKey": "IkivJ3XfidQ8kgxEu92zws8E6qgX3gzpBDaHS7Zqdt8=_review_805819759",
        "content": "Dear guests: Hello! Thank you very much for your review. Your satisfaction is our greatest motivation. We look forward to your visit again and wish you a happy life."
      }
    ]
  },
  "ServerData": null
}