{
  "data": {
    "commentTagV2List": [
      {
        "id": 1,
        "name": "Classy environment",
        "commentCount": 52,
        "type": 1
      },
      {
        "id": 84,
        "name": "Friendly front desk staff",
        "commentCount": 38,
        "type": 1
      },
      {
        "id": 32,
        "name": "Great amenities",
        "commentCount": 29,
        "type": 1
      },
      {
        "id": 6,
        "name": "Quiet & comfortable",
        "commentCount": 23,
        "type": 1
      },
      {
        "id": 53,
        "name": "Many amenities",
        "commentCount": 15,
        "type": 1
      },
      {
        "id": 149,
        "name": "Would stay again",
        "commentCount": 13,
        "type": 1
      },
      {
        "id": 70,
        "name": "Delicious breakfast",
        "commentCount": 6,
        "type": 1
      },
      {
        "id": 79,
        "name": "Convenient public transportation",
        "commentCount": 6,
        "type": 1
      }
    ],
    "commonStatisticList": [
      {
        "id": 1,
        "name": "All Reviews",
        "commentCount": 344
      },
      {
        "id": 2,
        "name": "Positive reviews",
        "commentCount": 341
      },
      {
        "id": 3,
        "name": "Negative reviews",
        "commentCount": 3
      },
      {
        "id": 6,
        "name": "Reviews with photos/video",
        "commentCount": 70
      }
    ],
    "totalCount": 258,
    "repeatCommentCount": 86,
    "commentList": [
      {
        "id": 919763135,
        "hotelId": 0,
        "videoList": [],
        "usefulCount": 0,
        "sourceLogoUrl": "",
        "language": "zh",
        "translatedContent": "",
        "securityKey": "QiJht7lWYmGtdadJQgBe/MYWkin4Uo5/IhYXM6Z5pKkHR6WKZjgqKg==_review_919763135",
        "canMarkUseful": true,
        "checkInDate": "2023-09-01 00:00:00",
        "content": "還行在貿大東門對面，就是價格高了些",
        "createDate": "2023-09-05 17:23:16",
        "imageList": [],
        "rating": 4,
        "commentLevel": "Very Good",
        "roomTypeName": "Superior 2-bed Room",
        "travelType": 30,
        "travelTypeText": "Family",
        "feedbackList": [
          {
            "content": "尊敬的賓客：很高興您在酒店和您的朋友們度過了一個美好的假期，您的點評是對我們服務最佳的肯定與鼓舞。我們還有很多優惠活動，請您繼續關注我們，歡迎您再次光臨",
            "translateContent": "",
            "securityKey": "MvdWBGSt8DxOYj8e+VxDAtHgDpUJ0Ycs3ABC6HmoZ/IHR6WKZjgqKg==_review_920122553"
          }
        ],
        "userInfo": {
          "headPictureUrl": "http://dimg04.c-ctrip.com/images/Z80q0v000000jmf90B344_C_130_130_Q70.jpg",
          "commentCount": 2,
          "nickName": "Guest User"
        },
        "beforeDecorationText": "",
        "translateFromRealReview": ""
      },
      {
        "id": 985966359,
        "hotelId": 0,
        "videoList": [],
        "usefulCount": 0,
        "sourceLogoUrl": "",
        "language": "zh",
        "translatedContent": "",
        "securityKey": "EcwX2zKN4rYkSzTaKcJaTnBHcAK8A3/dXUyzi/aa9AoHR6WKZjgqKg==_review_985966359",
        "canMarkUseful": true,
        "checkInDate": "2023-11-01 00:00:00",
        "content": "房間乾淨，服務人員非常好",
        "createDate": "2023-12-01 15:15:41",
        "imageList": [],
        "rating": 5,
        "commentLevel": "Outstanding",
        "roomTypeName": "Deluxe Queen Room",
        "travelType": 10,
        "travelTypeText": "Business travelers",
        "feedbackList": [
          {
            "content": "尊敬的賓客，非常感謝您對我們酒店的好評，我們會再接再厲不辜負您的好評，再次感謝您對酒店的肯定，期待再次光臨，祝旅途愉快",
            "translateContent": "",
            "securityKey": "KWqrNhUWWJn4Og0eh+gsvU+/+mNGqnJP2E7kKIFWGjUHR6WKZjgqKg==_review_986565783"
          }
        ],
        "userInfo": {
          "headPictureUrl": "http://dimg04.c-ctrip.com/images/Z80i0v000000jjy9b405A_C_130_130_Q70.jpg",
          "commentCount": 5,
          "nickName": "Guest User"
        },
        "beforeDecorationText": "",
        "translateFromRealReview": ""
      },
      {
        "id": 595588415,
        "hotelId": 0,
        "videoList": [],
        "usefulCount": 0,
        "sourceLogoUrl": "",
        "language": "zh",
        "translatedContent": "",
        "securityKey": "nWcZLfJfg+CpXgsI9F1m6xPX9ZcirmEAdIa3UizSBH8HR6WKZjgqKg==_review_595588415",
        "canMarkUseful": true,
        "checkInDate": "2022-06-01 00:00:00",
        "content": "從低風險地區來北京的第一晚，原本訂的酒店在一個社區裏，但社區卡點無法進入，打電話預訂，前台李娟小姐姐非常耐心的引導入住，讓人感受十分温暖，即使在異地，入住漢庭外經貿店，也像回家一樣！",
        "createDate": "2022-06-14 15:26:37",
        "imageList": [],
        "rating": 5,
        "commentLevel": "Outstanding",
        "roomTypeName": "2-bed Room",
        "travelType": 10,
        "travelTypeText": "Business travelers",
        "feedbackList": [
          {
            "content": "尊敬的客人，感謝您對我們工作的認可及肯定。 愛乾淨，住漢庭”是我們多年不變的的口號及工作內容。漢庭北京對外經貿大學酒店嚴格遵守華住集團的愛乾淨的條款，致力於為客人打造良好的酒店環境。漢庭北京對外經貿大學酒店坐落於北京北四環交通十分便利，臨近中日友好醫院，性價高。感謝您百忙之中為華住漢庭北京對外經貿大學酒店做評論。祝您諸事順利。",
            "translateContent": "",
            "securityKey": "EXl6ytIUXn2315kF2fQFJBbqyOcy/Jm3CgZ07xHFEn0HR6WKZjgqKg==_review_595599550"
          }
        ],
        "userInfo": {
          "headPictureUrl": "http://dimg04.c-ctrip.com/images/0AS25120009wz63zdC6FA_C_130_130_Q70.jpg",
          "commentCount": 6,
          "nickName": "Guest User"
        },
        "beforeDecorationText": "",
        "translateFromRealReview": ""
      },
      {
        "id": 831605485,
        "hotelId": 0,
        "videoList": [],
        "usefulCount": 0,
        "sourceLogoUrl": "",
        "language": "zh",
        "translatedContent": "",
        "securityKey": "YVdfMyf++XU4nrMsH6PSgyg0ixDJ0/AZfKFrp2anVisHR6WKZjgqKg==_review_831605485",
        "canMarkUseful": true,
        "checkInDate": "2023-06-01 00:00:00",
        "content": "房間舒適整潔乾淨，服務非常熱情周到，很滿意。",
        "createDate": "2023-06-16 14:46:20",
        "imageList": [],
        "rating": 5,
        "commentLevel": "Outstanding",
        "roomTypeName": "Superior 2-bed Room",
        "travelType": 30,
        "travelTypeText": "Family",
        "feedbackList": [
          {
            "content": "尊敬的客人，感謝您對我們工作的認可及肯定。 愛乾淨，住漢庭”是我們多年不變的的口號及工作內容。漢庭北京對外經貿大學酒店嚴格遵守華住集團的愛乾淨的條款，致力於為客人打造良好的酒店環境。漢庭北京對外經貿大學酒店坐落於北京北四環交通十分便利，臨近中日友好醫院，性價高。感謝您百忙之中為華住漢庭北京對外經貿大學酒店做評論。祝您諸事順利。",
            "translateContent": "",
            "securityKey": "EXl6ytIUXn2315kF2fQFJBbqyOcy/Jm3CgZ07xHFEn0HR6WKZjgqKg==_review_832791837"
          }
        ],
        "userInfo": {
          "headPictureUrl": "http://dimg04.c-ctrip.com/images/Z8050v000000jnn3hF304_C_130_130_Q70.jpg",
          "commentCount": 1,
          "nickName": "Guest User"
        },
        "beforeDecorationText": "",
        "translateFromRealReview": ""
      },
      {
        "id": 794982669,
        "hotelId": 0,
        "videoList": [],
        "usefulCount": 0,
        "sourceLogoUrl": "",
        "language": "zh",
        "translatedContent": "",
        "securityKey": "Y7cPdTYKSzZBP1tI948/AAWdWgC2dO470coFt45JqVMHR6WKZjgqKg==_review_794982669",
        "canMarkUseful": true,
        "checkInDate": "2023-04-01 00:00:00",
        "content": "環境不錯，交通也很方便，五一出遊，沒踩雷，你值得擁有",
        "createDate": "2023-05-12 21:47:34",
        "imageList": [],
        "rating": 5,
        "commentLevel": "Outstanding",
        "roomTypeName": "Queen Room",
        "travelType": 40,
        "travelTypeText": "Friends",
        "feedbackList": [
          {
            "content": "尊敬的賓客，非常感謝您對我們酒店的好評，我們會再接再厲不辜負您的好評，再次感謝您對酒店的肯定，期待再次光臨，祝旅途愉快",
            "translateContent": "",
            "securityKey": "KWqrNhUWWJn4Og0eh+gsvU+/+mNGqnJP2E7kKIFWGjUHR6WKZjgqKg==_review_795060275"
          }
        ],
        "userInfo": {
          "headPictureUrl": "http://dimg04.c-ctrip.com/images/Z80q0v000000jmf90B344_C_130_130_Q70.jpg",
          "commentCount": 3,
          "nickName": "Honey-you"
        },
        "beforeDecorationText": "",
        "translateFromRealReview": ""
      },
      {
        "id": 806348597,
        "hotelId": 0,
        "videoList": [],
        "usefulCount": 0,
        "sourceLogoUrl": "",
        "language": "zh",
        "translatedContent": "",
        "securityKey": "G1CLHzynt/YTkJL/qjFpGU7ukWx6CTuwY7kI2Glf5T4HR6WKZjgqKg==_review_806348597",
        "canMarkUseful": true,
        "checkInDate": "2023-05-01 00:00:00",
        "content": "很不錯的一個小酒店，服務員很熱情，房間很乾凈！",
        "createDate": "2023-05-29 08:29:51",
        "imageList": [],
        "rating": 5,
        "commentLevel": "Outstanding",
        "roomTypeName": "Family Room",
        "travelType": 50,
        "travelTypeText": "Solo travelers",
        "feedbackList": [
          {
            "content": "尊敬的賓客，非常感謝您對我們酒店的好評，我們會再接再厲不辜負您的好評，再次感謝您對酒店的肯定，期待再次光臨，祝旅途愉快",
            "translateContent": "",
            "securityKey": "KWqrNhUWWJn4Og0eh+gsvU+/+mNGqnJP2E7kKIFWGjUHR6WKZjgqKg==_review_806913095"
          }
        ],
        "userInfo": {
          "headPictureUrl": "http://dimg04.c-ctrip.com/images/0AS27120009wz6aovB7AA_C_130_130_Q70.png",
          "commentCount": 1,
          "nickName": "Anonymous User"
        },
        "beforeDecorationText": "",
        "translateFromRealReview": ""
      },
      {
        "id": 782810165,
        "hotelId": 0,
        "videoList": [],
        "usefulCount": 0,
        "sourceLogoUrl": "",
        "language": "zh",
        "translatedContent": "",
        "securityKey": "QbKsXvXVhUZ2JAGzcPA/9Wp2BbT5uHxy5TDHGlCfVIEHR6WKZjgqKg==_review_782810165",
        "canMarkUseful": true,
        "checkInDate": "2023-04-01 00:00:00",
        "content": "房間整潔乾淨，環境也較為安靜，地理位置好找，很不錯",
        "createDate": "2023-04-30 12:42:17",
        "imageList": [],
        "rating": 5,
        "commentLevel": "Outstanding",
        "roomTypeName": "Queen Room",
        "travelType": 10,
        "travelTypeText": "Business travelers",
        "feedbackList": [
          {
            "content": "尊敬的賓客，非常感謝您對我們酒店的好評，我們會再接再厲不辜負您的好評，再次感謝您對酒店的肯定，期待再次光臨，祝旅途愉快",
            "translateContent": "",
            "securityKey": "KWqrNhUWWJn4Og0eh+gsvU+/+mNGqnJP2E7kKIFWGjUHR6WKZjgqKg==_review_783323821"
          }
        ],
        "userInfo": {
          "headPictureUrl": "http://dimg04.c-ctrip.com/images/0AS25120009wz63zdC6FA_C_130_130_Q70.jpg",
          "commentCount": 2,
          "nickName": "Guest User"
        },
        "beforeDecorationText": "",
        "translateFromRealReview": ""
      },
      {
        "id": 806526047,
        "hotelId": 0,
        "videoList": [],
        "usefulCount": 0,
        "sourceLogoUrl": "",
        "language": "zh",
        "translatedContent": "",
        "securityKey": "oFH/XsCQABcrn8ysCu+43MG0lQYSdlb7zEmCgEoiqQEHR6WKZjgqKg==_review_806526047",
        "canMarkUseful": true,
        "checkInDate": "2023-05-01 00:00:00",
        "content": "服務態度很好～給升了個房，裝修簡潔，乾淨衞生",
        "createDate": "2023-05-29 13:22:47",
        "imageList": [],
        "rating": 5,
        "commentLevel": "Outstanding",
        "roomTypeName": "Deluxe Queen Room",
        "travelType": 50,
        "travelTypeText": "Solo travelers",
        "feedbackList": [
          {
            "content": "尊敬的賓客，非常感謝您對我們酒店的好評，我們會再接再厲不辜負您的好評，再次感謝您對酒店的肯定，期待再次光臨，祝旅途愉快",
            "translateContent": "",
            "securityKey": "KWqrNhUWWJn4Og0eh+gsvU+/+mNGqnJP2E7kKIFWGjUHR6WKZjgqKg==_review_806913103"
          }
        ],
        "userInfo": {
          "headPictureUrl": "http://dimg04.c-ctrip.com/images/0AS27120009wz6aovB7AA_C_130_130_Q70.jpg",
          "commentCount": 1,
          "nickName": "Guest User"
        },
        "beforeDecorationText": "",
        "translateFromRealReview": ""
      },
      {
        "id": 940540717,
        "hotelId": 0,
        "videoList": [],
        "usefulCount": 0,
        "sourceLogoUrl": "",
        "language": "zh",
        "translatedContent": "",
        "securityKey": "4SpEIgHUebrcZXHgkfQjoqzS0VmqsmN5blqtc+5IU2EHR6WKZjgqKg==_review_940540717",
        "canMarkUseful": true,
        "checkInDate": "2023-10-01 00:00:00",
        "content": "服務態度很好，房間乾淨整潔",
        "createDate": "2023-10-03 11:41:07",
        "imageList": [],
        "rating": 5,
        "commentLevel": "Outstanding",
        "roomTypeName": "Superior Queen Room",
        "travelType": 30,
        "travelTypeText": "Family",
        "feedbackList": [
          {
            "content": "尊敬的賓客，非常感謝您對我們酒店的好評，我們會再接再厲不辜負您的好評，再次感謝您對酒店的肯定，期待再次光臨，祝旅途愉快",
            "translateContent": "",
            "securityKey": "KWqrNhUWWJn4Og0eh+gsvU+/+mNGqnJP2E7kKIFWGjUHR6WKZjgqKg==_review_941368867"
          }
        ],
        "userInfo": {
          "headPictureUrl": "http://dimg04.c-ctrip.com/images/1h63l12000cao0k119859_C_130_130_Q70.jpg",
          "commentCount": 4,
          "nickName": "Guest User"
        },
        "beforeDecorationText": "",
        "translateFromRealReview": ""
      },
      {
        "id": 992569967,
        "hotelId": 0,
        "videoList": [],
        "usefulCount": 0,
        "sourceLogoUrl": "",
        "language": "zh",
        "translatedContent": "",
        "securityKey": "YL7dbx7DMYcy3wyenngBhbRCxZ2XawRbk1ieojY1AM0HR6WKZjgqKg==_review_992569967",
        "canMarkUseful": true,
        "checkInDate": "2023-12-01 00:00:00",
        "content": "房間乾淨，地理位置好",
        "createDate": "2023-12-10 17:40:45",
        "imageList": [],
        "rating": 5,
        "commentLevel": "Outstanding",
        "roomTypeName": "Superior Queen Room",
        "travelType": 10,
        "travelTypeText": "Business travelers",
        "feedbackList": [
          {
            "content": "尊敬的賓客，非常感謝您對我們酒店的好評，我們會再接再厲不辜負您的好評，再次感謝您對酒店的肯定，期待再次光臨，祝旅途愉快",
            "translateContent": "",
            "securityKey": "KWqrNhUWWJn4Og0eh+gsvU+/+mNGqnJP2E7kKIFWGjUHR6WKZjgqKg==_review_992897847"
          }
        ],
        "userInfo": {
          "headPictureUrl": "http://dimg04.c-ctrip.com/images/Z8010v000000jy23y696A_C_130_130_Q70.jpg",
          "commentCount": 7,
          "nickName": "Tanchangaidehua"
        },
        "beforeDecorationText": "",
        "translateFromRealReview": ""
      }
    ],
    "imageDomain": "ak-d.tripcdn.com",
    "grayHitVersion": "TARGET"
  },
  "ResponseStatus": {
    "Timestamp": "/Date(1703417142237+800)/",
    "Ack": "Success",
    "Errors": [],
    "Extension": [
      {
        "Id": "CLOGGING_TRACE_ID",
        "Value": ""
      },
      {
        "Id": "TraceLogId",
        "Value": "100044815-0a63cb34-473171-208417"
      },
      {
        "Id": "XRequestId",
        "Value": "3fe6536f-9d92-4e76-b841-cdf7630f07f5"
      },
      {
        "Id": "RootMessageId",
        "Value": "100025527-0a3d52d6-473171-652083"
      }
    ]
  }
}