{"Result":true,"ErrorMessage":null,"ErrorCode":0,"Response":{"transArray":[{"transKey":"0CrxYUc1hwX1ccWppMqsOyXVbsZnFoaZ5vWPPzzP5yoHR6WKZjgqKg==_review_464999044","content":"The breakfast is very curious, that is, there are too many people, and four people need to share a table. The internet speed is okay, there are few free movies on TV, and the traffic location of Sanyuan Bridge in Beijing is so good, the price/performance ratio is very high. There is a shopping center on the side to solve the problem."}]},"ServerData":null}