{"Result":true,"ErrorMessage":null,"ErrorCode":0,"Response":{"transArray":[{"transKey":"YgujT8AH5fDgCkbkb09DPddorkRzBakXsSsOGdLpOzoHR6WKZjgqKg==_review_471899781","content":"I have stayed here many times, and I especially recommend it to young couples and girlfriends who are traveling. The room is clean and tidy, the facilities are very user-friendly, the hair dryer works well, and the bed and pillows are moderately soft and firm. I am particularly satisfied that the TV has a kiwi industry version, and many movies can be watched for free."}]},"ServerData":null}