{"Result":true,"ErrorMessage":null,"ErrorCode":0,"Response":{"transArray":[{"transKey":"o69PeYGbNxgo2xiOHrI5gIDtwBvlYslMV70mxKSuvhQHR6WKZjgqKg==_review_499001747","content":"Apart from the good location, everything else is average. The room is not ventilated and has a strange smell. When I moved in on the first day, I found that a bottle of water had been opened, and the water in it was obviously missing a sip. There was no shower gel when I took a shower on the last day, and the cleaning lady didn't check it when cleaning?"}]},"ServerData":null}