{
  "Result": true,
  "ErrorMessage": null,
  "ErrorCode": 0,
  "Response": {
    "transArray": [
      {
        "transKey": "J140hfchvABLSe7AjOo+Nqz9I1zS0XGRLAtye67IZlwHR6WKZjgqKg==_review_988459465",
        "content": "There was a pungent smell when I first entered the door. I had to open the windows and open the door to allow convection for a while to dissipate the smell."
      },
      {
        "transKey": "oL/l6TotvzH4b1LqgPodK2kQ5yk+sHM4hBE0TTbLS0YHR6WKZjgqKg==_review_989189007",
        "content": "Thank you for choosing Hanting! I am very ashamed to have left a flaw in your stay experience this time. I would like to apologize to you. I hope you will give us another chance to serve you again. We will give priority to serving you better and wish you a happy life."
      }
    ]
  },
  "ServerData": null
}