{
  "Result": true,
  "ErrorMessage": null,
  "ErrorCode": 0,
  "Response": {
    "transArray": [
      {
        "transKey": "RyC8hPr6SwkYBxjhllYIDPaMNTosAI1uoW8UE4YLl2MHR6WKZjgqKg==_review_486991546",
        "content": "The hotel has a good location, convenient transportation, and good service. There is a free parking lot in the store. The four-hour breakfast is really great! I will stay at their house when I go to Beijing on business in the future!"
      },
      {
        "transKey": "xBmi5F67f5ecsg3dM+nCKtZjIKeP/5McLyjjGRshSYsHR6WKZjgqKg==_review_487074984",
        "content": "Hello dear guest! Thank you for choosing to stay at Orange Beijing Wukesong Hotel and for your recognition of the hotel's environment and services. Your satisfaction is the driving force for our progress. The hotel is located in the Badali Automobile Park on the Fourth Ring Road. It shares parking spaces with the park. There are sufficient parking spaces and is close to You can park for free by just picking up an electronic parking ticket at the front desk when you are in the store. Public transportation is easily accessible around the hotel, making it your best choice for business trips and accommodations. All the hotel staff look forward to your every visit and wish you success in your work!"
      }
    ]
  },
  "ServerData": null
}